dnfjson.py
dnfjson-0.3.1.data/scripts/dnfjson.py
dnfjson-0.3.1.dist-info/LICENSE
dnfjson-0.3.1.dist-info/METADATA
dnfjson-0.3.1.dist-info/WHEEL
dnfjson-0.3.1.dist-info/top_level.txt
dnfjson-0.3.1.dist-info/RECORD
